suromi/__init__.py
suromi/curses.py
suromi/utils.py
suHacku-1.0.0.dist-info/METADATA
suHacku-1.0.0.dist-info/WHEEL
suHacku-1.0.0.dist-info/top_level.txt
suHacku-1.0.0.dist-info/RECORD
