Metadata-Version: 2.1
Name: suHacku
Version: 1.0.0
Summary: a little package that can print diferent curses
Home-page: https://hack4u.io/
Author: Yato_kun
